spymarine/__init__.py
spymarine/communication.py
spymarine/device.py
spymarine/device_reader.py
spymarine/error.py
spymarine/property_dict.py
spymarine/py.typed
spymarine/sensor.py
spymarine-0.7.0.dist-info/METADATA
spymarine-0.7.0.dist-info/WHEEL
spymarine-0.7.0.dist-info/licenses/LICENSE
spymarine-0.7.0.dist-info/RECORD
