Metadata-Version: 2.4
Name: spymarine
Version: 0.7.0
Summary: Communicate with Simarine devices using asyncio and Python
Project-URL: Source code, https://github.com/christopher-strack/spymarine
Project-URL: Documentation, https://github.com/christopher-strack/spymarine/tree/main#readme
Author-email: Christopher Strack <christopher.strack@gmail.com>
License-Expression: MIT
License-File: LICENSE
Requires-Python: >=3.11
